NXModToolkit/__init__.py
NXModToolkit/__main__.py
NXModToolkit/creator/__init__.py
NXModToolkit/packager/__init__.py
NXModToolkit-1.0.1.dist-info/METADATA
NXModToolkit-1.0.1.dist-info/WHEEL
NXModToolkit-1.0.1.dist-info/entry_points.txt
NXModToolkit-1.0.1.dist-info/namespace_packages.txt
NXModToolkit-1.0.1.dist-info/top_level.txt
NXModToolkit-1.0.1.dist-info/zip-safe
NXModToolkit-1.0.1.dist-info/RECORD
